{
  "schemaVersion": 1,
  "type": "car",
  "id": "car-rial-arc1",
  "slug": "rial-arc1",
  "status": "published",
  "title": {
    "zh": "Rial ARC1",
    "en": "Rial ARC1"
  },
  "summary": {
    "zh": "Rial ARC1 是里亚尔打造的 F1 赛车。它参加了 1988 赛季的世界锦标赛。动力单元为 Ford Cosworth DFZ。",
    "en": "Rial ARC1, the F1 car of the 1988 season built by rial."
  },
  "sourceIds": ["source-wikipedia-1988-f1-season"],
  "updatedAt": "2026-07-14T12:00:00.000Z",
  "seasonIds": ["season-1988"],
  "constructorId": "team-rial",
  "driverIds": ["person-andrea-de-cesaris"],
  "technologyIds": [],
  "engine": "Ford Cosworth DFZ",
  "specifications": {
    "chassis": {
      "zh": "Rial ARC1 底盘。",
      "en": "Rial ARC1 chassis."
    },
    "engine": {
      "zh": "Ford Cosworth DFZ 3.5 升 V8 引擎。",
      "en": "Ford Cosworth DFZ 3.5-litre V8 engine."
    }
  },
  "blocks": [
    {
      "id": "rial-arc1-story",
      "type": "richText",
      "heading": {
        "zh": "赛车简介"
      },
      "content": {
        "zh": "Rial ARC1 是里亚尔打造的 F1 赛车。它参加了 1988 赛季的世界锦标赛。动力单元为 Ford Cosworth DFZ。主要车手为安德烈亚·德·切萨里斯。Rial ARC1 反映了其所在年代的规则与技术水平，是 F1 赛车演进链条上的一环。"
      }
    }
  ]
}
