{
  "schemaVersion": 1,
  "type": "car",
  "id": "car-lotus-102d",
  "slug": "lotus-102d",
  "status": "published",
  "title": {
    "zh": "莲花 102D",
    "en": "Lotus 102D"
  },
  "summary": {
    "zh": "莲花 102D 是莲花为 1992 赛季打造的 F1 赛车。动力单元为 Ford HBA5。",
    "en": "Lotus 102D, the Formula One car Lotus entered in the 1992 season. Powered by Ford HBA5."
  },
  "sourceIds": ["source-wikipedia-1992-f1-season"],
  "updatedAt": "2026-07-22T12:00:00.000Z",
  "seasonIds": ["season-1992"],
  "constructorId": "team-lotus",
  "driverIds": ["person-mika-hakkinen", "person-johnny-herbert"],
  "technologyIds": [],
  "engine": "Ford HBA5",
  "specifications": {
    "chassis": {
      "zh": "Lotus 102D 底盘",
      "en": "Lotus 102D chassis"
    },
    "engine": {
      "zh": "Ford HBA5 引擎",
      "en": "Ford HBA5 engine"
    }
  },
  "blocks": [
    {
      "id": "lotus-102d-story",
      "type": "richText",
      "heading": {
        "zh": "赛车简介"
      },
      "content": {
        "zh": "莲花 102D 是莲花为 1992 赛季打造的 F1 赛车，动力单元为 Ford HBA5。它是当年参赛阵容的一员，反映了所在年代的规则与技术水平。"
      }
    }
  ]
}
