{
  "schemaVersion": 1,
  "type": "car",
  "id": "car-ferrari-312t2",
  "slug": "ferrari-312t2",
  "status": "published",
  "title": {
    "zh": "法拉利 312T2",
    "en": "Ferrari 312T2"
  },
  "summary": {
    "zh": "1977 赛季冠军赛车。",
    "en": "The championship-winning car of the 1977 season."
  },
  "sourceIds": ["source-f1com-results-1977"],
  "updatedAt": "2026-07-12T12:00:00.000Z",
  "seasonIds": ["season-1977"],
  "constructorId": "team-ferrari",
  "driverIds": ["person-niki-lauda"],
  "technologyIds": ["technology-cosworth-dfv-era"],
  "engine": "Ferrari Flat-12",
  "specifications": {
    "engine": {
      "zh": "Ferrari Flat-12",
      "en": "Ferrari Flat-12"
    }
  },
  "blocks": []
}
