{
  "schemaVersion": 1,
  "type": "car",
  "id": "car-sauber-c30",
  "slug": "sauber-c30",
  "status": "published",
  "title": {
    "zh": "索伯 C30",
    "en": "Sauber C30"
  },
  "summary": {
    "zh": "索伯 C30 是索伯为 2011 赛季打造的 F1 赛车。动力单元为 Ferrari 056。",
    "en": "Sauber C30, the Formula One car Sauber entered in the 2011 season. Powered by Ferrari 056."
  },
  "sourceIds": ["source-wikipedia-2011-f1-season"],
  "updatedAt": "2026-07-22T12:00:00.000Z",
  "seasonIds": ["season-2011"],
  "constructorId": "team-sauber",
  "driverIds": [
    "person-kamui-kobayashi",
    "person-sergio-perez",
    "person-pedro-de-la-rosa"
  ],
  "technologyIds": [],
  "engine": "Ferrari 056",
  "specifications": {
    "chassis": {
      "zh": "Sauber C30 底盘",
      "en": "Sauber C30 chassis"
    },
    "engine": {
      "zh": "Ferrari 056 引擎",
      "en": "Ferrari 056 engine"
    }
  },
  "blocks": [
    {
      "id": "sauber-c30-story",
      "type": "richText",
      "heading": {
        "zh": "赛车简介"
      },
      "content": {
        "zh": "索伯 C30 是索伯为 2011 赛季打造的 F1 赛车，动力单元为 Ferrari 056。它是当年参赛阵容的一员，反映了所在年代的规则与技术水平。"
      }
    }
  ]
}
