{
  "schemaVersion": 1,
  "type": "person",
  "id": "person-dick-rathmann",
  "slug": "dick-rathmann",
  "status": "published",
  "title": {
    "zh": "Dick Rathmann",
    "en": "Dick Rathmann"
  },
  "summary": {
    "zh": "美国车手Dick Rathmann，活跃于 1956 赛季，效力于库尔蒂斯·克拉夫特。",
    "en": "American driver Dick Rathmann, active in 1956, racing for kurtis-kraft."
  },
  "sourceIds": ["source-wikipedia-1950s-f1-calendar"],
  "blocks": [
    {
      "id": "dick-rathmann-bio",
      "type": "richText",
      "heading": {
        "zh": "参赛生涯"
      },
      "content": {
        "zh": "Dick Rathmann是一位美国籍F1 车手。于 1956 赛季登场的 F1 锦标赛。代表库尔蒂斯·克拉夫特出战车队。虽未夺得世界冠军，但其 1 个赛季的参赛经历，仍是 F1 历史拼图的一部分。"
      }
    }
  ],
  "updatedAt": "2026-07-14T12:00:00.000Z",
  "personKind": "driver",
  "nationality": "American",
  "teamIds": ["team-kurtis-kraft"],
  "representativeSeasonIds": ["season-1956"],
  "championshipYears": [],
  "coverMediaId": "media-web-dick-rathmann-photo"
}
