{
  "schemaVersion": 1,
  "type": "mediaAsset",
  "id": "media-book-p0087-fig001",
  "kind": "image",
  "src": "/images/book/p0087_fig001.jpg",
  "alt": {
    "zh": "2012款迈肌伦MP427赛车展示了康达效应排气的原理。蓝色笛头代表来自底板和车身的气流，它们用于引导废气流（红色管头）(GiorgioPiola/Motorsport Images)",
    "en": "Technical illustration from the book (p.87)"
  },
  "caption": {
    "zh": "2012款迈肌伦MP427赛车展示了康达效应排气的原理。蓝色笛头代表来自底板和车身的气流，它们用于引导废气流（红色管头）(GiorgioPiola/Motorsport Images)（出自《图解 F1 赛车工程技术》）",
    "en": "Illustration from 《图解 F1 赛车工程技术》 (p.87)"
  },
  "credit": "出自《图解 F1 赛车工程技术》",
  "rights": {
    "status": "licensed",
    "sourceUrl": "https://www.cmpbook.com/"
  }
}
