{
  "schemaVersion": 1,
  "type": "mediaAsset",
  "id": "media-book-p0089-fig001",
  "kind": "image",
  "src": "/images/book/p0089_fig001.jpg",
  "alt": {
    "zh": "图为夏尔·勒克莱尔驾映的2022赛季法拉利F1-75赛车.可见覆盖车身面板接缝的股带（Motoreport Images)",
    "en": "Technical illustration from the book (p.89)"
  },
  "caption": {
    "zh": "图为夏尔·勒克莱尔驾映的2022赛季法拉利F1-75赛车.可见覆盖车身面板接缝的股带（Motoreport Images)（出自《图解 F1 赛车工程技术》）",
    "en": "Illustration from 《图解 F1 赛车工程技术》 (p.89)"
  },
  "credit": "出自《图解 F1 赛车工程技术》",
  "rights": {
    "status": "licensed",
    "sourceUrl": "https://www.cmpbook.com/"
  }
}
