{
  "schemaVersion": 1,
  "type": "mediaAsset",
  "id": "media-book-p0314-fig001",
  "kind": "image",
  "src": "/images/book/p0314_fig001.jpg",
  "alt": {
    "zh": "阿斯顿·马丁AMR22 赛车是季中研发的绝佳案例，它在2022赛季初期采用了图示的侧箱设计（摄于艾米利亚·罗马涅大奖赛周五练习赛期间）（Motorsport Images)",
    "en": "Technical illustration from the book (p.314)"
  },
  "caption": {
    "zh": "阿斯顿·马丁AMR22 赛车是季中研发的绝佳案例，它在2022赛季初期采用了图示的侧箱设计（摄于艾米利亚·罗马涅大奖赛周五练习赛期间）（Motorsport Images)（出自《图解 F1 赛车工程技术》）",
    "en": "Illustration from 《图解 F1 赛车工程技术》 (p.314)"
  },
  "credit": "出自《图解 F1 赛车工程技术》",
  "rights": {
    "status": "licensed",
    "sourceUrl": "https://www.cmpbook.com/"
  }
}
