{
  "schemaVersion": 1,
  "type": "era",
  "id": "era-2000s",
  "slug": "2000s",
  "status": "published",
  "title": {
    "zh": "2000 年代",
    "en": "2000s"
  },
  "summary": {
    "zh": "舒马赫与法拉利开启了这十年的统治，F2004 凭借卓越的气动效率与普利司通轮胎刷新多条赛道纪录；米其林与普利司通的轮胎大战推动圈速持续攀升；2006 年规则降排量到 2.4 升 V8；2009 年 KERS（动能回收）与双层扩散器同台登场，布朗 GP 从本田的废墟中横空出世夺冠。",
    "en": "Schumacher and Ferrari opened the decade in command, the F2004 setting lap records with superb aero efficiency and Bridgestone tyres; the Michelin–Bridgestone tyre war kept pushing lap times up; the 2006 rules downsized to 2.4-litre V8s; in 2009 KERS and the double-deck diffuser arrived together as Brawn GP rose from Honda's ashes to take the title."
  },
  "sourceIds": [
    "source-wikipedia-2000s-f1-calendar",
    "source-book-f1-illustrated-engineering"
  ],
  "blocks": [
    {
      "id": "era-2000s-story",
      "type": "richText",
      "heading": {
        "zh": "2000 年代的十年"
      },
      "content": {
        "zh": "2000 年代（约 2000–2009 年）是 F1 历史上的一个十年阶段。这一时期见证了引擎规则、空气动力学与安全理念的演变：从赛车构型到赛事组织，每个十年都为 F1 留下了独特的印记。下方概述概括了这十年的技术走向与代表人物。"
      },
      "sourceIds": ["source-book-f1-illustrated-engineering"]
    }
  ],
  "updatedAt": "2026-07-14T12:00:00.000Z",
  "startYear": 2000,
  "endYear": 2009,
  "color": "#2e8b57",
  "seasonIds": [
    "season-2000",
    "season-2001",
    "season-2002",
    "season-2003",
    "season-2004",
    "season-2005",
    "season-2006",
    "season-2007",
    "season-2008",
    "season-2009"
  ]
}
