{
  "schemaVersion": 1,
  "type": "race",
  "id": "race-1953-zandvoort-r3",
  "slug": "1953-zandvoort-r3",
  "status": "published",
  "title": {
    "zh": "1953 荷兰大奖赛",
    "en": "1953 Dutch Grand Prix"
  },
  "summary": {
    "zh": "1953 赛季第 3 站分站赛。",
    "en": "Round 3 of the 1953 championship."
  },
  "sourceIds": ["source-f1com-results-1953"],
  "blocks": [],
  "updatedAt": "2026-07-12T12:00:00.000Z",
  "seasonId": "season-1953",
  "circuitId": "circuit-zandvoort",
  "round": 3,
  "date": "1953-06-07",
  "winnerPersonId": "person-alberto-ascari",
  "winnerCarId": "car-ferrari-500-1953"
}
